__init__.py
data_grimorium/__init__.py
data_grimorium/bigquery_connector/__init__.py
data_grimorium/bigquery_connector/bigquery_connector.py
data_grimorium/bigquery_connector/bigquery_types.py
data_grimorium/data_preparation/__init__.py
data_grimorium/data_preparation/data_preparation_types.py
data_grimorium/data_preparation/data_preparation_utils.py
data_grimorium/general_utils/__init__.py
data_grimorium/general_utils/general_utils.py
data_grimorium/postgresql_connector/__init__.py
data_grimorium/postgresql_connector/postgresql_connector.py
data_grimorium/postgresql_connector/postgresql_types.py
data_grimorium-1.0.6.dist-info/licenses/LICENSE
data_grimorium-1.0.6.dist-info/METADATA
data_grimorium-1.0.6.dist-info/WHEEL
data_grimorium-1.0.6.dist-info/top_level.txt
data_grimorium-1.0.6.dist-info/RECORD
