Metadata-Version: 2.4
Name: data-grimorium
Version: 1.0.6
Summary: Data Grimorium is a collection of utilities for Data Scientists and Machine Learning Engineers, designed to streamline workflows and accelerate day-to-day coding tasks.
Author-email: Simone Porreca <porrecasimone@gmail.com>
License-Expression: GPL-3.0
Project-URL: Repository, https://github.com/Volscente/DataGrimorium
Project-URL: Backlog, https://github.com/users/Volscente/projects/16
Project-URL: Changelog, https://github.com/Volscente/DataGrimorium/blob/main/CHANGELOG.md
Keywords: Machine Learning,ML,Python,Data Science,DS
Classifier: Development Status :: 2 - Pre-Alpha
Classifier: Framework :: Pytest
Classifier: Intended Audience :: Developers
Classifier: Programming Language :: Python :: 3
Classifier: Topic :: Scientific/Engineering :: Artificial Intelligence
Requires-Python: >=3.13
License-File: LICENSE
Requires-Dist: db-dtypes>=1.4.3
Requires-Dist: dynaconf>=3.2.12
Requires-Dist: google-cloud-bigquery>=3.38.0
Requires-Dist: pandas>=2.3.3
Requires-Dist: pandas-stubs~=2.3.3
Requires-Dist: psycopg2>=2.9.11
Requires-Dist: pydantic>=2.12.3
Requires-Dist: scikit-learn>=1.7.2
Requires-Dist: sentence-transformers>=5.1.2
Requires-Dist: sqlalchemy>=2.0.44
Dynamic: license-file
